padding_tool.py
padding_tool-1.0.4.dist-info/licenses/LICENSE
padding_tool-1.0.4.dist-info/METADATA
padding_tool-1.0.4.dist-info/WHEEL
padding_tool-1.0.4.dist-info/entry_points.txt
padding_tool-1.0.4.dist-info/top_level.txt
padding_tool-1.0.4.dist-info/RECORD
