Metadata-Version: 2.4
Name: padding-tool
Version: 1.0.4
Summary: A simple Python CLI tool to pad a binary file to a specified size using a given byte value.
Author: Gil Weisbord
License: MIT
Requires-Python: >=3.6
License-File: LICENSE
Dynamic: license-file
Dynamic: requires-python
